{
  "76356f8345c2cd8234d497b93ac2fa12806af6e066cf96ba0f1a17a674f4635c": {
    "sourceId": "76356f8345c2cd8234d497b93ac2fa12806af6e066cf96ba0f1a17a674f4635c",
    "reproducibleGitChecksum": "d9e2a3c633f0652e795bba9483defca4eed0c8c65c38dfc554d94059a4784586",
    "entries": [
      {
        "GitRepo": "https://github.com/tianon/dockerfiles.git",
        "GitFetch": "refs/heads/master",
        "GitCommit": "bb8e613883f674afdf27e1036172a4eb2af0dd34",
        "Directory": "infosiftr-moby",
        "File": "Dockerfile",
        "Builder": "",
        "SOURCE_DATE_EPOCH": 1762472968
      }
    ],
    "arches": {
      "amd64": {
        "tags": [
          "infosiftr/moby:23.0.18",
          "infosiftr/moby:23.0",
          "infosiftr/moby:23",
          "infosiftr/moby:latest",
          "infosiftr/moby:amd64"
        ],
        "archTags": [],
        "froms": [
          "debian:trixie-slim"
        ],
        "lastStageFrom": "debian:trixie-slim",
        "platformString": "linux/amd64",
        "platform": {
          "architecture": "amd64",
          "os": "linux"
        },
        "parents": {
          "debian:trixie-slim": {
            "sourceId": null,
            "pin": null
          }
        }
      },
      "arm32v5": {
        "tags": [
          "infosiftr/moby:23.0.18",
          "infosiftr/moby:23.0",
          "infosiftr/moby:23",
          "infosiftr/moby:latest",
          "infosiftr/moby:arm32v5"
        ],
        "archTags": [],
        "froms": [
          "debian:trixie-slim"
        ],
        "lastStageFrom": "debian:trixie-slim",
        "platformString": "linux/arm/v5",
        "platform": {
          "architecture": "arm",
          "os": "linux",
          "variant": "v5"
        },
        "parents": {
          "debian:trixie-slim": {
            "sourceId": null,
            "pin": null
          }
        }
      },
      "arm32v7": {
        "tags": [
          "infosiftr/moby:23.0.18",
          "infosiftr/moby:23.0",
          "infosiftr/moby:23",
          "infosiftr/moby:latest",
          "infosiftr/moby:arm32v7"
        ],
        "archTags": [],
        "froms": [
          "debian:trixie-slim"
        ],
        "lastStageFrom": "debian:trixie-slim",
        "platformString": "linux/arm/v7",
        "platform": {
          "architecture": "arm",
          "os": "linux",
          "variant": "v7"
        },
        "parents": {
          "debian:trixie-slim": {
            "sourceId": null,
            "pin": null
          }
        }
      },
      "arm64v8": {
        "tags": [
          "infosiftr/moby:23.0.18",
          "infosiftr/moby:23.0",
          "infosiftr/moby:23",
          "infosiftr/moby:latest",
          "infosiftr/moby:arm64v8"
        ],
        "archTags": [],
        "froms": [
          "debian:trixie-slim"
        ],
        "lastStageFrom": "debian:trixie-slim",
        "platformString": "linux/arm64/v8",
        "platform": {
          "architecture": "arm64",
          "os": "linux",
          "variant": "v8"
        },
        "parents": {
          "debian:trixie-slim": {
            "sourceId": null,
            "pin": null
          }
        }
      },
      "i386": {
        "tags": [
          "infosiftr/moby:23.0.18",
          "infosiftr/moby:23.0",
          "infosiftr/moby:23",
          "infosiftr/moby:latest",
          "infosiftr/moby:i386"
        ],
        "archTags": [],
        "froms": [
          "debian:trixie-slim"
        ],
        "lastStageFrom": "debian:trixie-slim",
        "platformString": "linux/386",
        "platform": {
          "architecture": "386",
          "os": "linux"
        },
        "parents": {
          "debian:trixie-slim": {
            "sourceId": null,
            "pin": null
          }
        }
      },
      "ppc64le": {
        "tags": [
          "infosiftr/moby:23.0.18",
          "infosiftr/moby:23.0",
          "infosiftr/moby:23",
          "infosiftr/moby:latest",
          "infosiftr/moby:ppc64le"
        ],
        "archTags": [],
        "froms": [
          "debian:trixie-slim"
        ],
        "lastStageFrom": "debian:trixie-slim",
        "platformString": "linux/ppc64le",
        "platform": {
          "architecture": "ppc64le",
          "os": "linux"
        },
        "parents": {
          "debian:trixie-slim": {
            "sourceId": null,
            "pin": null
          }
        }
      },
      "riscv64": {
        "tags": [
          "infosiftr/moby:23.0.18",
          "infosiftr/moby:23.0",
          "infosiftr/moby:23",
          "infosiftr/moby:latest",
          "infosiftr/moby:riscv64"
        ],
        "archTags": [],
        "froms": [
          "debian:trixie-slim"
        ],
        "lastStageFrom": "debian:trixie-slim",
        "platformString": "linux/riscv64",
        "platform": {
          "architecture": "riscv64",
          "os": "linux"
        },
        "parents": {
          "debian:trixie-slim": {
            "sourceId": null,
            "pin": null
          }
        }
      },
      "s390x": {
        "tags": [
          "infosiftr/moby:23.0.18",
          "infosiftr/moby:23.0",
          "infosiftr/moby:23",
          "infosiftr/moby:latest",
          "infosiftr/moby:s390x"
        ],
        "archTags": [],
        "froms": [
          "debian:trixie-slim"
        ],
        "lastStageFrom": "debian:trixie-slim",
        "platformString": "linux/s390x",
        "platform": {
          "architecture": "s390x",
          "os": "linux"
        },
        "parents": {
          "debian:trixie-slim": {
            "sourceId": null,
            "pin": null
          }
        }
      }
    }
  },
  "4edaa03c23a5cf3779ca49304015ee4c87549048f971b6bf319195c606a79043": {
    "sourceId": "4edaa03c23a5cf3779ca49304015ee4c87549048f971b6bf319195c606a79043",
    "reproducibleGitChecksum": "d9e2a3c633f0652e795bba9483defca4eed0c8c65c38dfc554d94059a4784586",
    "entries": [
      {
        "GitRepo": "https://github.com/tianon/dockerfiles.git",
        "GitFetch": "refs/heads/master",
        "GitCommit": "bb8e613883f674afdf27e1036172a4eb2af0dd34",
        "Directory": "infosiftr-moby",
        "File": "Dockerfile.bookworm",
        "Builder": "",
        "SOURCE_DATE_EPOCH": 1762472968
      }
    ],
    "arches": {
      "mips64le": {
        "tags": [
          "infosiftr/moby:23.0.18",
          "infosiftr/moby:23.0",
          "infosiftr/moby:23",
          "infosiftr/moby:latest",
          "infosiftr/moby:mips64le"
        ],
        "archTags": [],
        "froms": [
          "debian:bookworm-slim"
        ],
        "lastStageFrom": "debian:bookworm-slim",
        "platformString": "linux/mips64le",
        "platform": {
          "architecture": "mips64le",
          "os": "linux"
        },
        "parents": {
          "debian:bookworm-slim": {
            "sourceId": null,
            "pin": null
          }
        }
      }
    }
  }
}
